{
  "name": "prankcall",
  "repo": "codeactual/prankcall",
  "description": "Call a function periodically with backoff and other customization",
  "version": "0.1.0",
  "keywords": [
    "retry",
    "repeater",
    "pagination",
    "generator",
    "yield",
    "es6",
    "timeout",
    "sleep",
    "backoff",
    "exponential",
    "producer",
    "consumer"
  ],
  "dependencies": {
    "codeactual/require-component": "0.1.0",
    "codeactual/extend": "0.1.0",
    "visionmedia/configurable.js": "f87ca5f"
  },
  "main": "lib/component/main.js",
  "scripts": [
    "lib/component/main.js"
  ],
  "license": "MIT"
}
